openmarkets/__init__.py
openmarkets/__main__.py
openmarkets/core/__init__.py
openmarkets/core/config.py
openmarkets/core/constants.py
openmarkets/core/exceptions.py
openmarkets/core/fastmcp.py
openmarkets/core/serializers.py
openmarkets/core/server.py
openmarkets/core/types.py
openmarkets/py.typed
openmarkets/repositories/analysis.py
openmarkets/repositories/crypto.py
openmarkets/repositories/financials.py
openmarkets/repositories/funds.py
openmarkets/repositories/holdings.py
openmarkets/repositories/markets.py
openmarkets/repositories/options.py
openmarkets/repositories/sector_industry.py
openmarkets/repositories/stock.py
openmarkets/repositories/technical_analysis.py
openmarkets/schemas/__init__.py
openmarkets/schemas/analysis.py
openmarkets/schemas/company.py
openmarkets/schemas/crypto.py
openmarkets/schemas/financials.py
openmarkets/schemas/funds.py
openmarkets/schemas/holdings.py
openmarkets/schemas/markets.py
openmarkets/schemas/options.py
openmarkets/schemas/sector_industry.py
openmarkets/schemas/stock.py
openmarkets/schemas/technical_analysis.py
openmarkets/services/__init__.py
openmarkets/services/analysis.py
openmarkets/services/crypto.py
openmarkets/services/financials.py
openmarkets/services/funds.py
openmarkets/services/holdings.py
openmarkets/services/markets.py
openmarkets/services/options.py
openmarkets/services/sector_industry.py
openmarkets/services/stock.py
openmarkets/services/technical_analysis.py
openmarkets/services/utils.py
openmarkets-0.1.0.dev122.dist-info/WHEEL
openmarkets-0.1.0.dev122.dist-info/entry_points.txt
openmarkets-0.1.0.dev122.dist-info/METADATA
openmarkets-0.1.0.dev122.dist-info/RECORD
