Metadata-Version: 2.3
Name: openmarkets
Version: 0.1.0.dev122
Summary: OpenMarkets is a modular Model Context Protocol (MCP) server that unifies access to financial market data for AI, research, and quantitative finance. It offers robust APIs for historical prices, corporate actions, fundamentals, and more, enabling advanced agentic retrieval, RAG, and LLM-powered workflows.
Keywords: machinelearning,finance,investment,mcp,modelcontextprotocol,yahoo finance,financial data retrieval
Author: Dobri Danchev
License: AGPL-3.0-or-later
Classifier: License :: OSI Approved :: GNU Affero General Public License v3 or later (AGPLv3+)
Classifier: Development Status :: 3 - Alpha
Classifier: Operating System :: OS Independent
Classifier: Intended Audience :: Developers
Classifier: Intended Audience :: Financial and Insurance Industry
Classifier: Topic :: Office/Business :: Financial
Classifier: Topic :: Office/Business :: Financial :: Investment
Classifier: Topic :: Scientific/Engineering
Classifier: Topic :: Scientific/Engineering :: Artificial Intelligence
Classifier: Topic :: Scientific/Engineering :: Interface Engine/Protocol Translator
Classifier: Topic :: Software Development :: Libraries
Classifier: Topic :: Software Development :: Libraries :: Python Modules
Classifier: Programming Language :: Python
Classifier: Programming Language :: Python :: 3
Classifier: Programming Language :: Python :: 3.10
Classifier: Programming Language :: Python :: 3.11
Classifier: Programming Language :: Python :: 3.12
Classifier: Programming Language :: Python :: 3.13
Classifier: Programming Language :: Python :: 3.14
Classifier: Programming Language :: Python :: 3 :: Only
Requires-Dist: mcp[cli]>=1.25.0
Requires-Dist: yfinance>=1.0.0
Requires-Dist: lxml>=6.0.2
Requires-Dist: fastmcp>=2.14.1 ; extra == 'fastmcp'
Requires-Python: >=3.10
Project-URL: Documentation, https://danchev.github.io/openmarkets/
Project-URL: Homepage, https://openmarkets.dev
Project-URL: Issues, https://github.com/danchev/openmarkets/issues
Project-URL: Source, https://github.com/danchev/openmarkets
Provides-Extra: fastmcp
